canaudit/__init__.py
canaudit/audit_manager.py
canaudit/controller.py
canaudit/core/__init__.py
canaudit/core/base.py
canaudit/core/results.py
canaudit/formats/__init__.py
canaudit/formats/dbc/__init__.py
canaudit/formats/dbc/dbc_loader.py
canaudit/formats/trace/__init__.py
canaudit/formats/trace/candump_loader.py
canaudit/formats/trace/csv_loader.py
canaudit/modules/__init__.py
canaudit/modules/timing_audit.py
canaudit/parser.py
canaudit/reports.py
canaudit-0.1.0.dist-info/METADATA
canaudit-0.1.0.dist-info/WHEEL
canaudit-0.1.0.dist-info/RECORD
