Metadata-Version: 2.3
Name: canaudit
Version: 0.1.0
Summary: A stand-alone, offline, and OS-agnostic CAN security analysis tool.
License: MIT
Author: Feras A.
Author-email: hello@feras.dev
Requires-Python: >=3.10,<4.0
Classifier: License :: OSI Approved :: MIT License
Classifier: Programming Language :: Python :: 3
Classifier: Programming Language :: Python :: 3.10
Classifier: Programming Language :: Python :: 3.11
Classifier: Programming Language :: Python :: 3.12
Classifier: Programming Language :: Python :: 3.13
Provides-Extra: dev
Requires-Dist: black (>=24.0) ; extra == "dev"
Requires-Dist: cantools (>=40.2.2,<41.0.0)
Requires-Dist: flake8 (>=7.0) ; extra == "dev"
Requires-Dist: isort (>=5.12) ; extra == "dev"
Requires-Dist: jinja2 (>=3.1.6,<4.0.0)
Requires-Dist: mypy (>=1.8) ; extra == "dev"
Requires-Dist: pandas (>=2.2)
Requires-Dist: pre-commit (>=3.7) ; extra == "dev"
Requires-Dist: pytest (>=8.1) ; extra == "dev"
